pyrugged/__init__.py
pyrugged/bodies/__init__.py
pyrugged/bodies/body_rotating_frame_id.py
pyrugged/bodies/ellipse.py
pyrugged/bodies/ellipsoid.py
pyrugged/bodies/ellipsoid_id.py
pyrugged/bodies/extended_ellipsoid.py
pyrugged/bodies/geodesy.py
pyrugged/bodies/geodetic_point.py
pyrugged/bodies/normalized_geodetic_point.py
pyrugged/bodies/one_axis_ellipsoid.py
pyrugged/configuration/__init__.py
pyrugged/configuration/init_orekit.py
pyrugged/data/orekit-data-master/README.md
pyrugged/data/orekit-data-master/UTC-TAI.history
pyrugged/data/orekit-data-master/fes2004_Cnm-Snm.dat
pyrugged/data/orekit-data-master/itrf-versions.conf
pyrugged/data/orekit-data-master/update.sh
pyrugged/data/orekit-data-master/CSSI-Space-Weather-Data/SpaceWeather-All-v1.2.txt
pyrugged/data/orekit-data-master/DE-440-ephemerides/lnxp1990.440
pyrugged/data/orekit-data-master/Earth-Orientation-Parameters/IAU-1980/finals.all
pyrugged/data/orekit-data-master/Earth-Orientation-Parameters/IAU-2000/finals2000A.all
pyrugged/data/orekit-data-master/MSAFE/apr1999f10.txt
pyrugged/data/orekit-data-master/MSAFE/apr2000f10.txt
pyrugged/data/orekit-data-master/MSAFE/apr2001f10.txt
pyrugged/data/orekit-data-master/MSAFE/apr2002f10.txt
pyrugged/data/orekit-data-master/MSAFE/apr2003f10.txt
pyrugged/data/orekit-data-master/MSAFE/apr2004f10.txt
pyrugged/data/orekit-data-master/MSAFE/apr2005f10.txt
pyrugged/data/orekit-data-master/MSAFE/apr2006f10.txt
pyrugged/data/orekit-data-master/MSAFE/apr2007f10.txt
pyrugged/data/orekit-data-master/MSAFE/apr2008f10.txt
pyrugged/data/orekit-data-master/MSAFE/apr2009f10.txt
pyrugged/data/orekit-data-master/MSAFE/apr2010f10.txt
pyrugged/data/orekit-data-master/MSAFE/apr2011f10.txt
pyrugged/data/orekit-data-master/MSAFE/apr2012f10.txt
pyrugged/data/orekit-data-master/MSAFE/apr2013f10.txt
pyrugged/data/orekit-data-master/MSAFE/apr2014f10.txt
pyrugged/data/orekit-data-master/MSAFE/apr2015f10.txt
pyrugged-1.1.4.dist-info/METADATA
pyrugged-1.1.4.dist-info/WHEEL
pyrugged-1.1.4.dist-info/top_level.txt
pyrugged-1.1.4.dist-info/RECORD
pyrugged-1.1.4.dist-info/licenses/LICENSE
