Metadata-Version: 2.4
Name: pyRugged
Version: 1.1.4
Summary: A sensor to terrain mapping tool
Author-email: CS Group <pyrugged@csgroup.eu>
Project-URL: Homepage, https://gitlab.eopf.copernicus.eu/geolib/pyrugged
Project-URL: Documentation, https://geolib.pages.eopf.copernicus.eu/pyrugged/
Project-URL: Repository, https://gitlab.eopf.copernicus.eu/geolib/pyrugged.git
Project-URL: Issues, https://gitlab.eopf.copernicus.eu/geolib/pyrugged/-/issues
Project-URL: Changelog, https://gitlab.eopf.copernicus.eu/geolib/pyrugged/-/blob/main/CHANGELOG.md
Keywords: rugged,orekit,hipparchus
Classifier: Development Status :: 5 - Production/Stable
Classifier: License :: OSI Approved :: Apache Software License
Classifier: Programming Language :: Python :: 3
Requires-Python: >=3.8
License-File: LICENSE
Requires-Dist: numpy>=1.24.1
Requires-Dist: scipy>=1.10
Requires-Dist: orekit-jcc>=13.1.0
Dynamic: license-file
